yworks_helper/__init__.py
yworks_helper/core/__init__.py
yworks_helper/core/bp/__init__.py
yworks_helper/core/bp/generate_graph_widget.py
yworks_helper/core/dmo/__init__.py
yworks_helper/core/svc/__init__.py
yworks_helper/core/svc/key_by_label_loader.py
yworks_helper-0.1.9.dist-info/WHEEL
yworks_helper-0.1.9.dist-info/METADATA
yworks_helper-0.1.9.dist-info/RECORD
