Metadata-Version: 2.1
Name: yworks-helper
Version: 0.1.9
Summary: Helper Microservice to create yWorks Graphs in Jupyter
Author: Craig Trim
Author-email: craigtrim@gmail.com
Requires-Python: ==3.8.5
Classifier: Programming Language :: Python :: 3
Requires-Dist: baseblock
Requires-Dist: ipykernel
Requires-Dist: jupyter (>=1.0.0,<2.0.0)
Requires-Dist: yfiles_jupyter_graphs
